CHANGES.rst
CONTRIBUTORS.rst
MANIFEST.in
README.rst
setup.py
docs/LICENSE.GPL
docs/LICENSE.rst
src/collective/__init__.py
src/collective.task.egg-info/PKG-INFO
src/collective.task.egg-info/SOURCES.txt
src/collective.task.egg-info/dependency_links.txt
src/collective.task.egg-info/entry_points.txt
src/collective.task.egg-info/namespace_packages.txt
src/collective.task.egg-info/not-zip-safe
src/collective.task.egg-info/requires.txt
src/collective.task.egg-info/top_level.txt
src/collective/task/__init__.py
src/collective/task/adapters.py
src/collective/task/behaviors.py
src/collective/task/behaviors.zcml
src/collective/task/configure.zcml
src/collective/task/field.py
src/collective/task/interfaces.py
src/collective/task/profiles.zcml
src/collective/task/setuphandlers.py
src/collective/task/subscribers.py
src/collective/task/subscribers.zcml
src/collective/task/testing.py
src/collective/task/testing.zcml
src/collective/task/utility.py
src/collective/task/browser/__init__.py
src/collective/task/browser/batchactions.py
src/collective/task/browser/configure.zcml
src/collective/task/browser/table.py
src/collective/task/browser/table.zcml
src/collective/task/browser/viewlets.py
src/collective/task/browser/views.py
src/collective/task/browser/static/back_in_created.png
src/collective/task/browser/static/back_in_progress.png
src/collective/task/browser/static/back_in_realized.png
src/collective/task/browser/static/back_in_to_assign.png
src/collective/task/browser/static/back_in_to_do.png
src/collective/task/browser/static/collectivetask.css
src/collective/task/browser/static/do_closed.png
src/collective/task/browser/static/do_in_progress.png
src/collective/task/browser/static/do_realized.png
src/collective/task/browser/static/do_to_assign.png
src/collective/task/browser/static/do_to_do.png
src/collective/task/browser/static/task_icon.png
src/collective/task/browser/templates/demoview.pt
src/collective/task/browser/templates/list_tasks.pt
src/collective/task/browser/templates/task_parent.pt
src/collective/task/content/__init__.py
src/collective/task/content/configure.zcml
src/collective/task/content/task.py
src/collective/task/locales/en/LC_MESSAGES/collective.eeafaceted.batchactions.po
src/collective/task/locales/en/LC_MESSAGES/collective.task.po
src/collective/task/locales/en/LC_MESSAGES/plone.po
