Metadata-Version: 2.1
Name: collective.task
Version: 3.0.7
Summary: Tasks management for Plone.
Home-page: http://pypi.python.org/pypi/collective.task
Author: Cédric Messiant
Author-email: cedricmessiant@ecreall.com
License: GPL
Keywords: Plone Python
Platform: UNKNOWN
Classifier: Environment :: Web Environment
Classifier: Framework :: Plone
Classifier: Framework :: Plone :: 4.3
Classifier: Programming Language :: Python
Classifier: Programming Language :: Python :: 2.7
Provides-Extra: test
